README.rst
setup.py
yadisk_api/__init__.py
yadisk_api/client.py
yadisk_api/errors.py
yadisk_api/requester.py
yadisk_api.egg-info/PKG-INFO
yadisk_api.egg-info/SOURCES.txt
yadisk_api.egg-info/dependency_links.txt
yadisk_api.egg-info/requires.txt
yadisk_api.egg-info/top_level.txt