Metadata-Version: 1.1
Name: yadisk-api
Version: 1.0
Summary: Yandex.disk http api client
Home-page: https://github.com/freylis/yadisk-api
Author: Mikhail Volkov
Author-email: freylis2@gmail.com
License: MIT License
Platform: UNKNOWN
Classifier: Environment :: Web Environment
Classifier: Intended Audience :: Developers
Classifier: License :: OSI Approved :: MIT License
Classifier: Operating System :: OS Independent
Classifier: Programming Language :: Python :: 3
Classifier: Topic :: Internet :: WWW/HTTP
Classifier: Topic :: Internet :: WWW/HTTP :: Dynamic Content
Classifier: Topic :: Software Development :: Libraries
